gmadmin/__init__.py
gmadmin/cli.py
gmadmin/client.py
gmadmin/config.py
gmadmin/responses.py
gmadmin-0.1.3.dist-info/licenses/LICENSE
gmadmin-0.1.3.dist-info/METADATA
gmadmin-0.1.3.dist-info/WHEEL
gmadmin-0.1.3.dist-info/entry_points.txt
gmadmin-0.1.3.dist-info/top_level.txt
gmadmin-0.1.3.dist-info/RECORD
