Metadata-Version: 2.4
Name: gmadmin
Version: 0.1.3
Summary: Python client library and CLI for GLIMPS Malware Admin API
Author-email: GLIMPS Dev Core Team <contact@glimps.re>
Maintainer-email: GLIMPS Dev Core Team <contact@glimps.re>
License: MIT
Project-URL: Homepage, https://github.com/GLIMPS/gmadmin
Project-URL: Documentation, https://docs.glimps.re/gmadmin
Project-URL: Repository, https://github.com/GLIMPS/gmadmin.git
Project-URL: Issues, https://github.com/GLIMPS/gmadmin/issues
Project-URL: Changelog, https://github.com/GLIMPS/gmadmin/blob/main/CHANGELOG.md
Keywords: glimps,admin,api,cli,malware,analysis,security,management,rbac,user-management
Classifier: Development Status :: 4 - Beta
Classifier: Environment :: Console
Classifier: Intended Audience :: Developers
Classifier: Intended Audience :: System Administrators
Classifier: Intended Audience :: Information Technology
Classifier: License :: OSI Approved :: MIT License
Classifier: Operating System :: OS Independent
Classifier: Programming Language :: Python
Classifier: Programming Language :: Python :: 3
Classifier: Programming Language :: Python :: 3.10
Classifier: Programming Language :: Python :: 3.11
Classifier: Programming Language :: Python :: 3.12
Classifier: Programming Language :: Python :: 3.13
Classifier: Programming Language :: Python :: Implementation :: CPython
Classifier: Programming Language :: Python :: Implementation :: PyPy
Classifier: Topic :: Software Development :: Libraries
Classifier: Topic :: Software Development :: Libraries :: Python Modules
Classifier: Topic :: System :: Systems Administration
Classifier: Topic :: Security
Classifier: Topic :: Utilities
Classifier: Typing :: Typed
Requires-Python: >=3.10
License-File: LICENSE
Requires-Dist: click<9.0,>=8.0
Requires-Dist: click-default-group<2.0,>=1.2
Requires-Dist: requests<3.0,>=2.28
Requires-Dist: rich>=14.0
Requires-Dist: certifi>=2023.0.0
Requires-Dist: urllib3<3.0.0,>=2.0.0
Requires-Dist: dotenv>=0.9.9
Provides-Extra: dev
Requires-Dist: pytest>=7.0.0; extra == "dev"
Requires-Dist: pytest-cov>=4.0.0; extra == "dev"
Requires-Dist: pytest-mock>=3.10.0; extra == "dev"
Requires-Dist: pytest-timeout>=2.1.0; extra == "dev"
Requires-Dist: pytest-asyncio>=0.21.0; extra == "dev"
Requires-Dist: responses>=0.23.0; extra == "dev"
Requires-Dist: ruff>=0.1.0; extra == "dev"
Requires-Dist: black>=23.0.0; extra == "dev"
Requires-Dist: mypy>=1.0.0; extra == "dev"
Requires-Dist: types-requests>=2.28.0; extra == "dev"
Requires-Dist: tox>=4.0.0; extra == "dev"
Requires-Dist: pre-commit>=3.0.0; extra == "dev"
Provides-Extra: test
Requires-Dist: pytest>=7.0.0; extra == "test"
Requires-Dist: pytest-cov>=4.0.0; extra == "test"
Requires-Dist: pytest-mock>=3.10.0; extra == "test"
Requires-Dist: pytest-timeout>=2.1.0; extra == "test"
Requires-Dist: responses>=0.23.0; extra == "test"
Provides-Extra: lint
Requires-Dist: ruff>=0.1.0; extra == "lint"
Requires-Dist: black>=23.0.0; extra == "lint"
Requires-Dist: mypy>=1.0.0; extra == "lint"
Requires-Dist: types-requests>=2.28.0; extra == "lint"
Provides-Extra: docs
Requires-Dist: sphinx>=5.0.0; extra == "docs"
Requires-Dist: sphinx-rtd-theme>=1.0.0; extra == "docs"
Requires-Dist: sphinx-click>=4.0.0; extra == "docs"
Requires-Dist: sphinx-autodoc-typehints>=1.19.0; extra == "docs"
Provides-Extra: all
Requires-Dist: gmadmin[dev,docs,lint,test]; extra == "all"
Dynamic: license-file
